{
  "project_info": {
    "project_number": "237077892054",
    "project_id": "color-picker-camera",
    "storage_bucket": "color-picker-camera.appspot.com"
  },
  "client": [
    {
      "client_info": {
        "mobilesdk_app_id": "1:237077892054:android:07db74e50848ec98bdb277",
        "android_client_info": {
          "package_name": "com.colorpicker.colorpalette.colorstock.rbg.color.eyedropper"
        }
      },
      "oauth_client": [
        {
          "client_id": "237077892054-ejja1qaig5omnpuchebt9k5dmf34csnk.apps.googleusercontent.com",
          "client_type": 3
        }
      ],
      "api_key": [
        {
          "current_key": "AIzaSyA040iaX6gF9OvHsN4AgB-9d-oTt72jXyE"
        }
      ],
      "services": {
        "appinvite_service": {
          "other_platform_oauth_client": [
            {
              "client_id": "237077892054-ejja1qaig5omnpuchebt9k5dmf34csnk.apps.googleusercontent.com",
              "client_type": 3
            }
          ]
        }
      }
    }
  ],
  "configuration_version": "1"
}